studiopulsee/__init__.py
studiopulsee/cli.py
studiopulsee/debug.py
studiopulsee/event_stream.py
studiopulsee/job_settings.py
studiopulsee/app/__init__.py
studiopulsee/app/api.py
studiopulsee/app/config.py
studiopulsee/app/mixin.py
studiopulsee/app/swagger.py
studiopulsee/app/blueprints/__init__.py
studiopulsee/app/blueprints/assets/__init__.py
studiopulsee/app/blueprints/assets/resources.py
studiopulsee/app/blueprints/auth/__init__.py
studiopulsee/app/blueprints/auth/resources.py
studiopulsee/app/blueprints/breakdown/__init__.py
studiopulsee/app/blueprints/breakdown/resources.py
studiopulsee/app/blueprints/comments/__init__.py
studiopulsee/app/blueprints/comments/resources.py
studiopulsee/app/blueprints/crud/__init__.py
studiopulsee/app/blueprints/crud/asset_instance.py
studiopulsee/app/blueprints/crud/attachment_file.py
studiopulsee/app/blueprints/crud/base.py
studiopulsee/app/blueprints/crud/comments.py
studiopulsee/app/blueprints/crud/custom_action.py
studiopulsee/app/blueprints/crud/day_off.py
studiopulsee/app/blueprints/crud/department.py
studiopulsee/app/blueprints/crud/entity.py
studiopulsee/app/blueprints/crud/entity_link.py
studiopulsee/app/blueprints/crud/entity_type.py
studiopulsee/app/blueprints/crud/event.py
studiopulsee/app/blueprints/crud/file_status.py
studiopulsee/app/blueprints/crud/metadata_descriptor.py
studiopulsee/app/blueprints/crud/milestone.py
studiopulsee/app/blueprints/crud/news.py
studiopulsee/app/blueprints/crud/notification.py
studiopulsee/app/blueprints/crud/organisation.py
studiopulsee/app/blueprints/crud/output_file.py
studiopulsee/app/blueprints/crud/output_type.py
studiopulsee/app/blueprints/crud/person.py
studiopulsee/app/blueprints/crud/playlist.py
studiopulsee/app/blueprints/crud/preview_background_file.py
studiopulsee/app/blueprints/crud/preview_file.py
studiopulsee/app/blueprints/crud/project.py
studiopulsee/app/blueprints/crud/project_status.py
studiopulsee/app/blueprints/crud/schedule_item.py
studiopulsee-0.17.1.dist-info/METADATA
studiopulsee-0.17.1.dist-info/WHEEL
studiopulsee-0.17.1.dist-info/entry_points.txt
studiopulsee-0.17.1.dist-info/top_level.txt
studiopulsee-0.17.1.dist-info/RECORD
